format_time_engine-1.0.1.dist-info/licenses/LICENSE
parameters/__init__.py
parameters/manager.py
tests/edgecase/__init__.py
tests/edgecase/test_calendar_atomic_save_recovery.py
tests/edgecase/test_calendar_load_corruption_handling.py
tests/edgecase/test_maximum_rollover.py
tests/edgecase/test_moon_calendar_brightness_bounds.py
tests/edgecase/test_notifcation_fails_silently.py
tests/edgecase/test_notification_robustness.py
tests/edgecase/test_parameter_null_load_handling.py
tests/edgecase/test_time_advance_invalid_tick.py
tests/edgecase/test_unified_time_module_invalid_inputs.py
tests/integration/__init__.py
tests/integration/test_manager_on_change_to_unified_time.py
tests/integration/test_notification_broadcast_integration.py
tests/integration/test_notification_sent_on_time_change.py
tests/integration/test_notification_shutdown.py
tests/integration/test_time_to_api_query_consistency.py
tests/integration/test_unified_time_module_data_dir.py
tests/integration/test_unified_time_module_file_regeneration.py
tests/integration/test_unified_time_module_regeneration_flow.py
tests/module/__init__.py
tests/module/test_module_api.py
tests/module/test_module_clock.py
tests/module/test_module_manager.py
tests/module/test_module_moon_calendar.py
tests/module/test_module_notification.py
tests/module/test_module_sun_calendar.py
tests/module/test_module_time.py
tests/module/test_module_unified_time_model.py
tests/unit/__init__.py
tests/unit/test_api_mooncycleapi.py
tests/unit/test_api_suncycleapi.py
tests/unit/test_calendar_atomic_save.py
tests/unit/test_calendar_generate_reference.py
tests/unit/test_clock_main_behavior.py
tests/unit/test_manager_fallback_behavior.py
tests/unit/test_manager_get_invalid_path.py
tests/unit/test_manager_notify.py
tests/unit/test_manager_on_change.py
tests/unit/test_manager_on_change_overwrites.py
tests/unit/test_manager_set_and_get.py
tests/unit/test_manager_skip_notify_if_value_unchanged.py
tests/unit/test_moon_calendar_generate_and_query.py
tests/unit/test_notification_broadcast_unit.py
format_time_engine-1.0.1.dist-info/METADATA
format_time_engine-1.0.1.dist-info/WHEEL
format_time_engine-1.0.1.dist-info/entry_points.txt
format_time_engine-1.0.1.dist-info/top_level.txt
format_time_engine-1.0.1.dist-info/RECORD
