Metadata-Version: 2.4
Name: format_time_engine
Version: 1.0.1
Summary: A modular time and calendar engine with customizable ticks, sun/moon altitude tables, and dynamic parameter propagation.
Home-page: https://github.com/ProphetGang/format_time
Author: Simon DeFrisco
Author-email: formatlifeofficial@gmail.com
License: MIT
Classifier: Development Status :: 5 - Production/Stable
Classifier: Intended Audience :: Developers
Classifier: Topic :: Software Development :: Libraries
Classifier: Programming Language :: Python :: 3.12
Classifier: License :: OSI Approved :: MIT License
Classifier: Operating System :: OS Independent
Requires-Python: >=3.12
License-File: LICENSE
Requires-Dist: numpy
Requires-Dist: SQLAlchemy
Provides-Extra: geo
Requires-Dist: rasterio; extra == "geo"
Requires-Dist: scipy; extra == "geo"
Requires-Dist: geoPandas; extra == "geo"
Requires-Dist: shapely; extra == "geo"
Requires-Dist: pyproj; extra == "geo"
Provides-Extra: ui
Requires-Dist: PyQt5; extra == "ui"
Requires-Dist: matplotlib; extra == "ui"
Provides-Extra: dev
Requires-Dist: black; extra == "dev"
Requires-Dist: isort; extra == "dev"
Requires-Dist: flake8; extra == "dev"
Requires-Dist: pre-commit; extra == "dev"
Requires-Dist: pytest; extra == "dev"
Dynamic: author
Dynamic: author-email
Dynamic: classifier
Dynamic: description
Dynamic: description-content-type
Dynamic: home-page
Dynamic: license
Dynamic: license-file
Dynamic: provides-extra
Dynamic: requires-dist
Dynamic: requires-python
Dynamic: summary
